{
  "schemaVersion": 1,
  "generatedSurface": {
    "tables": [
      "account_deletions",
      "addon_features",
      "addons",
      "ai_copilot_conversations",
      "ai_copilot_messages",
      "ai_copilot_rate_limits",
      "approval_decisions",
      "ats_integrations",
      "candidates",
      "clock_events",
      "compliance_rulesets",
      "compliance_violations",
      "customer_success_health_scores",
      "customer_success_nps_surveys",
      "customer_success_onboarding_progress",
      "data_retention_policies",
      "document_templates",
      "email_queue",
      "email_send_log",
      "email_send_state",
      "email_unsubscribe_tokens",
      "engagement_achievements",
      "engagement_member_achievements",
      "engagement_streaks",
      "enterprise_access_decisions",
      "enterprise_access_requests",
      "enterprise_access_systems",
      "enterprise_access_template_systems",
      "enterprise_access_templates",
      "enterprise_agile_field_metadata",
      "enterprise_agile_issues",
      "enterprise_agile_sync_log",
      "enterprise_allowances",
      "enterprise_api_keys",
      "enterprise_api_usage_logs",
      "enterprise_approval_chains",
      "enterprise_attendance_audit",
      "enterprise_attendance_oncall_windows",
      "enterprise_attendance_payroll_exports",
      "enterprise_attendance_periods",
      "enterprise_attendance_schedule_templates",
      "enterprise_attendance_segments",
      "enterprise_audit_events",
      "enterprise_blocked_dates",
      "enterprise_calendar_sync_log",
      "enterprise_capacity_snapshots",
      "enterprise_catalog_categories",
      "enterprise_catalog_role_skills",
      "enterprise_catalog_roles",
      "enterprise_catalog_skills",
      "enterprise_company_leave_days",
      "enterprise_contract_types",
      "enterprise_daily_rules",
      "enterprise_decision_memory",
      "enterprise_embed_tokens",
      "enterprise_escalation_rules",
      "enterprise_export_jobs",
      "enterprise_feature_catalog",
      "enterprise_holidays",
      "enterprise_hr_workflow_instances",
      "enterprise_hr_workflow_tasks",
      "enterprise_hr_workflow_templates",
      "enterprise_ical_tokens",
      "enterprise_industries",
      "enterprise_integration_sync_log",
      "enterprise_invitations",
      "enterprise_job_families",
      "enterprise_leadership_levels",
      "enterprise_leave_quotas",
      "enterprise_leave_types",
      "enterprise_member_goals",
      "enterprise_member_rates",
      "enterprise_member_role_allocations",
      "enterprise_member_site_priorities",
      "enterprise_member_skills",
      "enterprise_member_templates",
      "enterprise_memberships",
      "enterprise_notification_preferences",
      "enterprise_notifications",
      "enterprise_office_coverage_rules",
      "enterprise_office_equipment",
      "enterprise_office_min_staffing",
      "enterprise_offices",
      "enterprise_onboarding_instances",
      "enterprise_onboarding_step_completions",
      "enterprise_onboarding_template_steps",
      "enterprise_onboarding_templates",
      "enterprise_open_shift_claims",
      "enterprise_open_shift_requests",
      "enterprise_open_shift_waitlist",
      "enterprise_org_chart_snapshots",
      "enterprise_org_units",
      "enterprise_project_assignments",
      "enterprise_project_rates",
      "enterprise_project_resource_requirements",
      "enterprise_project_skill_requirements",
      "enterprise_projects",
      "enterprise_quota_transactions",
      "enterprise_report_schedules",
      "enterprise_reports",
      "enterprise_role_definitions",
      "enterprise_role_permissions",
      "enterprise_rule_templates",
      "enterprise_scenario_assignments",
      "enterprise_scenarios",
      "enterprise_seed_config",
      "enterprise_shift_assignments",
      "enterprise_shift_cancellations",
      "enterprise_skills",
      "enterprise_staff_availability",
      "enterprise_team_roles",
      "enterprise_teams",
      "enterprise_translation_overrides",
      "enterprise_ui_section_states",
      "enterprise_user_calendar_integrations",
      "enterprise_webhook_deliveries",
      "enterprise_webhook_subscriptions",
      "enterprise_work_categories",
      "enterprise_workspace_integrations",
      "enterprise_workspace_role_categories",
      "enterprise_workspace_role_skills",
      "enterprise_workspace_roles",
      "enterprise_workspace_skills",
      "enterprise_workspaces",
      "event_participants",
      "event_share_tokens",
      "events",
      "favorites",
      "features",
      "friendships",
      "gdpr_requests",
      "generated_documents",
      "help_articles",
      "help_releases",
      "interview_slots",
      "leave_request_attachments",
      "leave_request_substitutes",
      "leave_requests",
      "marketplace_plugins",
      "payroll_export_configs",
      "payroll_periods",
      "personal_availability",
      "platform_audit_events",
      "platform_feature_flags",
      "plugin_webhook_events",
      "profiles",
      "qr_clock_sessions",
      "reseller_admins",
      "resellers",
      "shift_trade_acceptances",
      "shift_trade_offers",
      "suppressed_emails",
      "tenant_addons",
      "tenant_calendar_settings",
      "tenant_feature_overrides",
      "tenant_subscriptions",
      "tenant_workspaces",
      "tenants",
      "tier_features",
      "tiers",
      "user_roles",
      "votes",
      "wellbeing_alerts",
      "wellbeing_scores",
      "workspace_installed_plugins"
    ],
    "views": [
      "enterprise_coverage_rules",
      "enterprise_leave_quota_balances",
      "enterprise_org_pulse_membership",
      "workspace_active_tier"
    ],
    "functions": [
      "ai_copilot_start_conversation",
      "analytics_absence_risk_scores",
      "analytics_coverage_risk_heatmap",
      "analytics_labor_cost_forecast",
      "attendance_caller_membership",
      "attendance_can_edit_period",
      "attendance_delete_oncall_window",
      "attendance_delete_segment",
      "attendance_expected_hours_for_period",
      "attendance_get_or_create_period",
      "attendance_list_workspace_periods",
      "attendance_payroll_export",
      "attendance_recompute_totals",
      "attendance_record_export",
      "attendance_remove_site_assignment",
      "attendance_transition_period",
      "attendance_upsert_oncall_window",
      "attendance_upsert_segment",
      "attendance_upsert_site_assignment",
      "auto_archive_expired_coverage_rules",
      "calc_leave_days",
      "can_access_event",
      "cancel_open_shift_request",
      "cancel_shift_assignment",
      "candidate_create_slot",
      "candidate_generate_onboarding",
      "candidate_interview_slot_eligible",
      "candidate_self_book",
      "check_member_availability",
      "claim_open_shift",
      "clock_event",
      "clock_generate_qr",
      "compliance_check_working_time",
      "create_embed_token",
      "create_open_shift_request",
      "create_workspace_with_owner",
      "customer_success_calculate_health_score",
      "customer_success_record_onboarding_step",
      "customer_success_submit_nps",
      "customer_success_trigger_nps",
      "decline_open_shift_invitation",
      "delete_email",
      "document_generate",
      "document_substitute",
      "embed_assign_shift",
      "embed_remove_shift",
      "enforce_data_retention",
      "engagement_record_event",
      "enqueue_email",
      "get_embed_capacity_planner_data",
      "get_embed_view_data",
      "get_team_headcount",
      "get_user_ids_by_emails",
      "get_workspace_leave_for_export",
      "get_workspace_members_for_export",
      "has_enterprise_role",
      "has_role",
      "haversine_km",
      "hr_workflow_close_instance",
      "hr_workflow_create_instance",
      "hr_workflow_list_instances",
      "hr_workflow_update_task",
      "import_enterprise_catalog_to_workspace",
      "is_enterprise_member",
      "is_reseller_admin",
      "is_tenant_member",
      "join_open_shift_waitlist",
      "lock_payroll_period_snapshot",
      "mark_payroll_period_exported",
      "marketplace_install_plugin",
      "marketplace_set_plugin_status",
      "marketplace_submit_plugin",
      "marketplace_uninstall_plugin",
      "move_to_dlq",
      "process_open_shift_escalations",
      "read_email_batch",
      "reopen_payroll_period_break_glass",
      "require_feature_id",
      "reseller_get_usage",
      "reseller_provision_workspace",
      "reseller_update_theme",
      "revoke_embed_token",
      "seed_default_access_systems",
      "seed_default_contract_types",
      "seed_default_leadership_levels",
      "shift_trade_accept",
      "shift_trade_cancel",
      "shift_trade_decide",
      "shift_trade_is_eligible",
      "shift_trade_offer",
      "superadmin_change_workspace_tier",
      "tenant_enabled_features",
      "tenant_id_for_workspace",
      "validate_password_policy",
      "webhook_emit",
      "webhook_record_delivery",
      "wellbeing_calculate_scores",
      "wellbeing_get_weights",
      "workspace_permission_catalog"
    ],
    "enums": [
      "app_role",
      "enterprise_attendance_period_status",
      "enterprise_attendance_segment_type",
      "enterprise_experience_level",
      "enterprise_membership_status",
      "enterprise_role",
      "integration_provider",
      "leave_request_status",
      "leave_type",
      "quota_transaction_type",
      "substitute_status"
    ]
  },
  "unprovenGeneratedSurface": {
    "tables": [
      "ai_copilot_conversations",
      "ai_copilot_messages",
      "ai_copilot_rate_limits",
      "ats_integrations",
      "compliance_rulesets",
      "compliance_violations",
      "customer_success_health_scores",
      "customer_success_nps_surveys",
      "customer_success_onboarding_progress",
      "document_templates",
      "engagement_achievements",
      "engagement_member_achievements",
      "engagement_streaks",
      "enterprise_attendance_audit",
      "enterprise_attendance_oncall_windows",
      "enterprise_attendance_payroll_exports",
      "enterprise_attendance_periods",
      "enterprise_attendance_schedule_templates",
      "enterprise_attendance_segments",
      "enterprise_webhook_deliveries",
      "generated_documents",
      "reseller_admins",
      "resellers",
      "shift_trade_acceptances",
      "shift_trade_offers"
    ],
    "views": [
      "workspace_active_tier"
    ],
    "functions": [
      "ai_copilot_start_conversation",
      "analytics_absence_risk_scores",
      "analytics_coverage_risk_heatmap",
      "analytics_labor_cost_forecast",
      "attendance_caller_membership",
      "attendance_can_edit_period",
      "attendance_delete_oncall_window",
      "attendance_delete_segment",
      "attendance_expected_hours_for_period",
      "attendance_get_or_create_period",
      "attendance_list_workspace_periods",
      "attendance_payroll_export",
      "attendance_recompute_totals",
      "attendance_record_export",
      "attendance_transition_period",
      "attendance_upsert_oncall_window",
      "attendance_upsert_segment",
      "compliance_check_working_time",
      "customer_success_calculate_health_score",
      "customer_success_record_onboarding_step",
      "customer_success_submit_nps",
      "customer_success_trigger_nps",
      "document_generate",
      "engagement_record_event",
      "get_workspace_leave_for_export",
      "get_workspace_members_for_export",
      "import_enterprise_catalog_to_workspace",
      "is_reseller_admin",
      "reseller_get_usage",
      "reseller_provision_workspace",
      "reseller_update_theme",
      "shift_trade_accept",
      "shift_trade_cancel",
      "shift_trade_decide",
      "shift_trade_is_eligible",
      "shift_trade_offer",
      "webhook_emit",
      "webhook_record_delivery",
      "wellbeing_calculate_scores",
      "wellbeing_get_weights",
      "workspace_permission_catalog"
    ],
    "enums": [
      "enterprise_attendance_period_status",
      "enterprise_attendance_segment_type"
    ]
  }
}
